AUTHORS
ChangeLog
LICENSE.txt
README.md
config_sample.yml
requirements.txt
setup.cfg
setup.py
taskforge/__init__.py
taskforge/config.py
taskforge/persist.py
taskforge/plugin.py
taskforge.egg-info/PKG-INFO
taskforge.egg-info/SOURCES.txt
taskforge.egg-info/dependency_links.txt
taskforge.egg-info/entry_points.txt
taskforge.egg-info/not-zip-safe
taskforge.egg-info/requires.txt
taskforge.egg-info/top_level.txt
taskforge/commands/__init__.py
taskforge/commands/all.py
taskforge/commands/run.py
taskforge/plugins/__init__.py
taskforge/plugins/bugwarrior.py
taskforge/plugins/shorten.py