Metadata-Version: 1.1
Name: taskforge
Version: 0.1.1
Summary: Plugin-friendly workflow system for interacting with taskwarrior tasks
Home-page: "http://github.com/ryansb/taskgears"
Author: Ryan S. Brown
Author-email: sb@ryansb.com
License: AGPLv3
Keywords: taskwarrior
Platform: UNKNOWN
Classifier: Natural Language :: English
Classifier: Operating System :: POSIX :: Linux
Classifier: Programming Language :: Python :: 2.7
